flex_prompt/__init__.py
flex_prompt/cat.py
flex_prompt/context.py
flex_prompt/expect.py
flex_prompt/find_target.py
flex_prompt/flex.py
flex_prompt/render.py
flex_prompt/rendering.py
flex_prompt/target.py
flex_prompt/targets/__init__.py
flex_prompt/targets/openai.py
flex_prompt/targets/testing.py
flex_prompt-0.0.4.dist-info/METADATA
flex_prompt-0.0.4.dist-info/WHEEL
flex_prompt-0.0.4.dist-info/licenses/LICENSE
flex_prompt-0.0.4.dist-info/RECORD
