Metadata-Version: 2.1
Name: flex-prompt
Version: 0.0.4
Summary: a flexible prompt renderer for large language models (LLMs)
Project-URL: Homepage, https://github.com/queerviolet/flex-prompt
Project-URL: Issues, https://github.com/queerviolet/flex-prompt/issues
Author-email: ashi <i@ashi.io>
License-File: LICENSE
Classifier: Development Status :: 2 - Pre-Alpha
Classifier: License :: OSI Approved :: MIT License
Classifier: Operating System :: OS Independent
Classifier: Programming Language :: Python :: 3
Classifier: Programming Language :: Python :: 3.9
Classifier: Programming Language :: Python :: 3.10
Classifier: Programming Language :: Python :: 3.11
Requires-Python: >=3.8
Provides-Extra: openai
Requires-Dist: tiktoken; extra == 'openai'
